LICENSE
MANIFEST.in
README.md
setup.cfg
setup.py
pyiArduinoI2Cmatrix/WString.cpp
pyiArduinoI2Cmatrix/WString.h
pyiArduinoI2Cmatrix/additional_defines.h
pyiArduinoI2Cmatrix/dtostrf.cpp
pyiArduinoI2Cmatrix/dtostrf.h
pyiArduinoI2Cmatrix/iarduino_I2C_Matrix_8x8.cpp
pyiArduinoI2Cmatrix/iarduino_I2C_Matrix_8x8.h
pyiArduinoI2Cmatrix/iarduino_I2C_Matrix_8x8.pxd
pyiArduinoI2Cmatrix/iarduino_I2C_PI.cpp
pyiArduinoI2Cmatrix/iarduino_I2C_PI.h
pyiArduinoI2Cmatrix/itoa.cpp
pyiArduinoI2Cmatrix/itoa.h
pyiArduinoI2Cmatrix/pyiArduinoI2Cmatrix.cpp
pyiArduinoI2Cmatrix/pyiArduinoI2Cmatrix.pyx
pyiArduinoI2Cmatrix.egg-info/PKG-INFO
pyiArduinoI2Cmatrix.egg-info/SOURCES.txt
pyiArduinoI2Cmatrix.egg-info/dependency_links.txt
pyiArduinoI2Cmatrix.egg-info/top_level.txt
pyiArduinoI2Cmatrix/Cpp/Angle.cpp
pyiArduinoI2Cmatrix/Cpp/Blink.cpp
pyiArduinoI2Cmatrix/Cpp/BlinkAnimation.cpp
pyiArduinoI2Cmatrix/Cpp/Image.cpp
pyiArduinoI2Cmatrix/Cpp/PrintCharAnimationRus.cpp
pyiArduinoI2Cmatrix/Cpp/PrintTickerRus.cpp